leuci_lib/__init__.py
leuci_lib/atom.py
leuci_lib/interpolator.py
leuci_lib/mapfunctions.py
leuci_lib/maploader.py
leuci_lib/mapobject.py
leuci_lib/vectorthree.py
leuci_lib-1.1.6.dist-info/LICENSE
leuci_lib-1.1.6.dist-info/METADATA
leuci_lib-1.1.6.dist-info/WHEEL
leuci_lib-1.1.6.dist-info/top_level.txt
leuci_lib-1.1.6.dist-info/RECORD
